MANIFEST.in
README.md
setup.cfg
setup.py
brainly_scraper/__init__.py
brainly_scraper.egg-info/PKG-INFO
brainly_scraper.egg-info/SOURCES.txt
brainly_scraper.egg-info/dependency_links.txt
brainly_scraper.egg-info/requires.txt
brainly_scraper.egg-info/top_level.txt